rss_tube/__init__.py
rss_tube/__main__.py
rss_tube/__version__.py
rss_tube/default_settings.py
rss_tube/download.py
rss_tube/parser.py
rss_tube/tasks.py
rss_tube/updater.py
rss_tube/utils.py
rss_tube/database/__init__.py
rss_tube/database/cache.py
rss_tube/database/database.py
rss_tube/database/feeds.py
rss_tube/database/filters.py
rss_tube/database/settings.py
rss_tube/gui/AboutDialog.py
rss_tube/gui/FiltersWidget.py
rss_tube/gui/MainWindow.py
rss_tube/gui/MyTableWidget.py
rss_tube/gui/MyTreeWidget.py
rss_tube/gui/NewFeedDialog.py
rss_tube/gui/PurgeEntriesDialog.py
rss_tube/gui/PurgeExcludeDialog.py
rss_tube/gui/RenameDialog.py
rss_tube/gui/SearchWidget.py
rss_tube/gui/SettingsDialog.py
rss_tube/gui/ShortcutDialog.py
rss_tube/gui/StatisticsDialog.py
rss_tube/gui/Tray.py
rss_tube/gui/__init__.py
rss_tube/gui/EntryWidgets/BaseEntry.py
rss_tube/gui/EntryWidgets/EntrySoundcloud.py
rss_tube/gui/EntryWidgets/EntryYoutube.py
rss_tube/gui/EntryWidgets/__init__.py
rss_tube/gui/EntryWidgets/entry_actions.py
rss_tube/gui/designs/__init__.py
rss_tube/gui/designs/main_window.py
rss_tube/gui/designs/widget_filter.py
rss_tube/gui/designs/widget_filter_rule.py
rss_tube/gui/designs/widget_filters.py
rss_tube/gui/designs/widget_help.py
rss_tube/gui/designs/widget_new_feed.py
rss_tube/gui/designs/widget_purge_entries.py
rss_tube/gui/designs/widget_rename.py
rss_tube/gui/designs/widget_settings.py
rss_tube/gui/designs/widget_soundcloud.py
rss_tube/gui/designs/widget_youtube.py
rss_tube/gui/themes/__init__.py
rss_tube/gui/themes/dark/EntrySoundcloud.css
rss_tube/gui/themes/dark/EntryYoutube.css
rss_tube/gui/themes/dark/__init__.py
rss_tube/gui/themes/dark/audio.png
rss_tube/gui/themes/dark/category.svg
rss_tube/gui/themes/dark/category_new.svg
rss_tube/gui/themes/dark/dark.css
rss_tube/gui/themes/dark/feed_new.svg
rss_tube/gui/themes/dark/logo.png
rss_tube/gui/themes/dark/palette.py
rss_tube/gui/themes/dark/settings.svg
rss_tube/gui/themes/dark/soundcloud.svg
rsstube-0.6.15.dist-info/LICENSE
rsstube-0.6.15.dist-info/METADATA
rsstube-0.6.15.dist-info/WHEEL
rsstube-0.6.15.dist-info/entry_points.txt
rsstube-0.6.15.dist-info/top_level.txt
rsstube-0.6.15.dist-info/RECORD
