Metadata-Version: 2.1
Name: rsstube
Version: 0.6.15
Summary: A simple desktop application for Youtube, based on RSS feeds.
Home-page: https://github.com/seird/rsstube
Author: k.dries@protonmail.com
Author-email: k.dries@protonmail.com
License: GPLv3
Classifier: License :: OSI Approved :: GNU General Public License v3 (GPLv3)
Classifier: Programming Language :: Python
Classifier: Programming Language :: Python :: 3
Classifier: Programming Language :: Python :: 3.8
Classifier: Programming Language :: Python :: 3.9
Classifier: Programming Language :: Python :: 3.10
Requires-Python: >=3.8.0
License-File: LICENSE
Requires-Dist: requests
Requires-Dist: PyQt6
Requires-Dist: schedule
Requires-Dist: lxml
Requires-Dist: packaging
Provides-Extra: socks5_proxy
Requires-Dist: pysocks ; extra == 'socks5_proxy'
